Metadata-Version: 1.0
Name: Tolik
Version: 0.0
Summary: Gaussian and Binomial distributions
Home-page: UNKNOWN
Author: UNKNOWN
Author-email: KirillGlaz13@yandex.ru
License: UNKNOWN
Platform: UNKNOWN
